http_import/__init__.py
http_import/http_import.py
http_import-0.1.2.dist-info/LICENSE
http_import-0.1.2.dist-info/METADATA
http_import-0.1.2.dist-info/WHEEL
http_import-0.1.2.dist-info/top_level.txt
http_import-0.1.2.dist-info/RECORD
