Metadata-Version: 2.1
Name: http-import
Version: 0.1.2
Summary: The import module uses HTTP from the Internet 
Home-page: https://github.com/cn-kali-team/http_import
Author: Kali-Team
Author-email: root@kali-team.cn
License: MIT
Platform: UNKNOWN
Classifier: License :: OSI Approved :: MIT License
Classifier: Programming Language :: Python
Classifier: Programming Language :: Python :: 3
Classifier: Programming Language :: Python :: 3.6
Classifier: Programming Language :: Python :: Implementation :: CPython
Classifier: Programming Language :: Python :: Implementation :: PyPy
Requires-Python: >=3.6.0
